Act.03/alu.v
module alu(
    input [7:0] A,
    input [7:0] B,
    input [2:0] op_code,
    output reg [7:0] result,
    output reg zero_flag,
    output reg carry_flag
);

    wire [8:0] sum_result;
    assign sum_result = A + B;

    // Complemento a dos
    wire [7:0] b_comp2;
    assign b_comp2 = ~B + 1;
    wire [8:0] sub_result;
    assign sub_result = A + b_comp2;

    always @(*) begin
        result = 8'b0;
        zero_flag = 1'b0; //establecer un valor por defecto al inicio
        carry_flag = 1'b0; // the same

        case(op_code)
            // Suma: A + B
            3'b000: begin
                result = sum_result[7:0];
                carry_flag = sum_result[8];
                zero_flag = (result == 8'b0);
            end

            // Resta: A - B
            3'b001: begin
                result = sub_result[7:0];
                carry_flag = sub_result[8];
                zero_flag = (result == 8'b0);
            end

            // AND: A & B
            3'b010: begin
                result = A & B;
                zero_flag = (result == 8'b0);
            end

            // OR: A | B
            3'b011: begin
                result = A | B;
                zero_flag = (result == 8'b0);
            end

            // XOR: A ^ B
            3'b100: begin
                result = A ^ B;
                zero_flag = (result == 8'b0);
            end

            // Comparación (Igual): A == B
            3'b101: begin
                result = (A == B) ? 8'b1 : 8'b0;
                zero_flag = (result == 8'b0);
            end

            // Comparación: A > B
            3'b110: begin
                result = (sub_result[8]) ? 8'b1 : 8'b0;
                zero_flag = (result == 8'b0);
            end

            // Desplazamiento: A << 1
            3'b111: begin
                result = A << 1;
                zero_flag = (result == 8'b0);
            end

            default: begin
                result = 8'bX; // Valor por defecto en caso de un op_code no válido
                zero_flag = 1'bX;
                carry_flag = 1'bX;
            end
        endcase
    end
endmodule

Act.03/alu_tb.v
module alu_tb;

    reg [7:0] A;
    reg [7:0] B;
    reg [2:0] op_code;
    wire [7:0] result;
    wire zero_flag;
    wire carry_flag;

    alu dut (
        .A(A),
        .B(B),
        .op_code(op_code),
        .result(result),
        .zero_flag(zero_flag),
        .carry_flag(carry_flag)
    );

    initial begin
        $dumpfile("alu.vcd"); // Archivo de volcado para ver las formas de onda 
        $dumpvars(0, alu_tb);

        // Prueba de Suma (10 + 5 = 15)
        A = 8'd10;
        B = 8'd5;
        op_code = 3'b000;
        #10;

        // Prueba de Resta (20 - 7 = 13)
        A = 8'd20;
        B = 8'd7;
        op_code = 3'b001;
        #10;

        // Prueba de AND (5 & 3 = 1) 
        A = 8'd5;
        B = 8'd3;
        op_code = 3'b010;
        #10;

        // Prueba de OR (5 | 3 = 7)
        A = 8'd5;
        B = 8'd3;
        op_code = 3'b011;
        #10;

        // Prueba de XOR (5 ^ 3 = 6)
        A = 8'd5;
        B = 8'd3;
        op_code = 3'b100;
        #10;

        // Prueba de Igualdad (12 == 12)
        A = 8'd12;
        B = 8'd12;
        op_code = 3'b101;
        #10;

        // Prueba de Mayor que (15 > 8)
        A = 8'd15;
        B = 8'd8;
        op_code = 3'b110;
        #10;

        // Prueba de Desplazamiento (4 << 1 = 8)
        A = 8'd4; 
        B = 8'd0; // B no se usa 
        op_code = 3'b111;
        #10;

        $finish; 
    end
endmodule

Act.03/alu.vcd
$date
	Sat Sep 06 16:52:22 2025
$end
$version
	ModelSim Version 2020.1
$end
$timescale
	1ps
$end

$scope module alu_tb $end
$var reg 8 ! A [7:0] $end
$var reg 8 " B [7:0] $end
$var reg 3 # op_code [2:0] $end
$var wire 1 $ result [7] $end
$var wire 1 % result [6] $end
$var wire 1 & result [5] $end
$var wire 1 ' result [4] $end
$var wire 1 ( result [3] $end
$var wire 1 ) result [2] $end
$var wire 1 * result [1] $end
$var wire 1 + result [0] $end
$var wire 1 , zero_flag $end
$var wire 1 - carry_flag $end

$scope module dut $end
$var wire 1 . A [7] $end
$var wire 1 / A [6] $end
$var wire 1 0 A [5] $end
$var wire 1 1 A [4] $end
$var wire 1 2 A [3] $end
$var wire 1 3 A [2] $end
$var wire 1 4 A [1] $end
$var wire 1 5 A [0] $end
$var wire 1 6 B [7] $end
$var wire 1 7 B [6] $end
$var wire 1 8 B [5] $end
$var wire 1 9 B [4] $end
$var wire 1 : B [3] $end
$var wire 1 ; B [2] $end
$var wire 1 < B [1] $end
$var wire 1 = B [0] $end
$var wire 1 > op_code [2] $end
$var wire 1 ? op_code [1] $end
$var wire 1 @ op_code [0] $end
$var reg 8 A result [7:0] $end
$var reg 1 B zero_flag $end
$var reg 1 C carry_flag $end
$var wire 1 D sum_result [8] $end
$var wire 1 E sum_result [7] $end
$var wire 1 F sum_result [6] $end
$var wire 1 G sum_result [5] $end
$var wire 1 H sum_result [4] $end
$var wire 1 I sum_result [3] $end
$var wire 1 J sum_result [2] $end
$var wire 1 K sum_result [1] $end
$var wire 1 L sum_result [0] $end
$var wire 1 M b_comp2 [7] $end
$var wire 1 N b_comp2 [6] $end
$var wire 1 O b_comp2 [5] $end
$var wire 1 P b_comp2 [4] $end
$var wire 1 Q b_comp2 [3] $end
$var wire 1 R b_comp2 [2] $end
$var wire 1 S b_comp2 [1] $end
$var wire 1 T b_comp2 [0] $end
$var wire 1 U sub_result [8] $end
$var wire 1 V sub_result [7] $end
$var wire 1 W sub_result [6] $end
$var wire 1 X sub_result [5] $end
$var wire 1 Y sub_result [4] $end
$var wire 1 Z sub_result [3] $end
$var wire 1 [ sub_result [2] $end
$var wire 1 \ sub_result [1] $end
$var wire 1 ] sub_result [0] $end
$upscope $end
$upscope $end
$enddefinitions $end
#0
$dumpvars
b1010 !
b101 "
b0 #
b1111 A
0B
0C
1+
1*
1)
1(
0'
0&
0%
0$
0,
0-
1L
1K
1J
1I
0H
0G
0F
0E
0D
1T
1S
0R
1Q
1P
1O
1N
1M
1]
0\
1[
0Z
0Y
0X
0W
0V
1U
0@
0?
0>
1=
0<
1;
0:
09
08
07
06
05
14
03
12
01
00
0/
0.
$end
#10
b10100 !
b111 "
b1 #
1@
1<
04
13
02
11
0S
1Z
0J
1H
b0 A
b1101 A
1C
0*
1-
#20
b101 !
b11 "
b10 #
0@
1?
0;
15
01
1R
0]
1\
0[
0Z
0L
0K
0H
b0 A
0C
b1 A
0)
0(
0-
#30
b11 #
1@
b0 A
b111 A
1*
1)
#40
b100 #
0@
0?
1>
b0 A
b110 A
0+
#50
b1100 !
b1100 "
b101 #
1@
0=
0<
1;
1:
05
12
0T
0Q
0\
1H
b0 A
b1 A
1+
0*
0)
#60
b1111 !
b1000 "
b110 #
0@
1?
0;
15
14
0R
1Q
1]
1\
1[
1L
1K
1J
0I
b0 A
b1 A
#70
b100 !
b0 "
b111 #
1@
0:
05
04
02
0Q
0P
0O
0N
0M
0]
0\
0U
0L
0K
0H
b0 A
b1000 A
0+
1(
